forms_fieldset/__init__.py
forms_fieldset/admin.py
forms_fieldset/apps.py
forms_fieldset/models.py
forms_fieldset/tests.py
forms_fieldset/views.py
forms_fieldset/migrations/__init__.py
forms_fieldset/static/forms_fieldset/css/fonts.css
forms_fieldset/static/forms_fieldset/css/main.css
forms_fieldset/static/forms_fieldset/fonts/LICENSE.txt
forms_fieldset/static/forms_fieldset/fonts/README.txt
forms_fieldset/static/forms_fieldset/fonts/Roboto-Bold-webfont.woff
forms_fieldset/static/forms_fieldset/fonts/Roboto-Light-webfont.woff
forms_fieldset/static/forms_fieldset/fonts/Roboto-Regular-webfont.woff
forms_fieldset/static/forms_fieldset/img/README.txt
forms_fieldset/static/forms_fieldset/img/calendar-icons.svg
forms_fieldset/static/forms_fieldset/img/icon-addlink.svg
forms_fieldset/static/forms_fieldset/img/icon-alert.svg
forms_fieldset/static/forms_fieldset/img/icon-calendar.svg
forms_fieldset/static/forms_fieldset/img/icon-changelink.svg
forms_fieldset/static/forms_fieldset/img/icon-clock.svg
forms_fieldset/static/forms_fieldset/img/icon-deletelink.svg
forms_fieldset/static/forms_fieldset/img/icon-no.svg
forms_fieldset/static/forms_fieldset/img/icon-unknown-alt.svg
forms_fieldset/static/forms_fieldset/img/icon-unknown.svg
forms_fieldset/static/forms_fieldset/img/icon-viewlink.svg
forms_fieldset/static/forms_fieldset/img/icon-yes.svg
forms_fieldset/static/forms_fieldset/img/inline-delete.svg
forms_fieldset/static/forms_fieldset/img/search.svg
forms_fieldset/static/forms_fieldset/img/selector-icons.svg
forms_fieldset/static/forms_fieldset/img/sorting-icons.svg
forms_fieldset/static/forms_fieldset/img/tooltag-add.svg
forms_fieldset/static/forms_fieldset/img/tooltag-arrowright.svg
forms_fieldset/templates/forms_fieldset/fieldset.html
forms_fieldset/templates/forms_fieldset/tabular.html
forms_fieldset/templatetags/__init__.py
forms_fieldset/templatetags/forms_fieldset.py
django5_forms_fieldset-1.0.0.dist-info/LICENSE
django5_forms_fieldset-1.0.0.dist-info/METADATA
django5_forms_fieldset-1.0.0.dist-info/WHEEL
django5_forms_fieldset-1.0.0.dist-info/top_level.txt
django5_forms_fieldset-1.0.0.dist-info/RECORD
