Metadata-Version: 2.2
Name: django5-forms-fieldset
Version: 1.0.0
Summary: Django form fieldset inspire django admin fieldset. (fork of original reposity by hadpro24 to support Django 5.1 and newer releases)
Home-page: https://github.com/NCIAdmin/django5-forms-fieldset
Author: Harouna Diallo forked and maintained by NCI IT Team
Author-email: itservice@ncicap.org
License: BSD-3-Clause
Classifier: Environment :: Console
Classifier: Intended Audience :: Developers
Classifier: License :: OSI Approved :: BSD License
Classifier: Operating System :: OS Independent
Classifier: Programming Language :: Python :: 3
Classifier: Programming Language :: Python :: 3 :: Only
Classifier: Programming Language :: Python :: 3.6
Classifier: Programming Language :: Python :: 3.7
Classifier: Programming Language :: Python :: 3.8
Classifier: Programming Language :: Python :: 3.9
Classifier: Programming Language :: Python :: 3.10
Classifier: Programming Language :: Python :: 3.11
Classifier: Programming Language :: Python :: 3.12
License-File: LICENSE
Dynamic: description
Dynamic: description-content-type
